MTLA.py
mtla-0.2.0.dist-info/LICENSE
mtla-0.2.0.dist-info/METADATA
mtla-0.2.0.dist-info/NOTICE
mtla-0.2.0.dist-info/WHEEL
mtla-0.2.0.dist-info/top_level.txt
mtla-0.2.0.dist-info/RECORD
