Metadata-Version: 2.1
Name: mtla
Version: 0.2.0
Summary: Multihead Temporal Latent Attention implementation
Author-email: Keqi Deng <kd502@cam.ac.uk>
License: Apache-2.0
Project-URL: Homepage, https://github.com/D-Keqi/mtla
Project-URL: Repository, https://github.com/D-Keqi/mtla
Project-URL: BugTracker, https://github.com/D-Keqi/mtla/issues
Project-URL: Documentation, https://github.com/D-Keqi/mtla#readme
Classifier: Development Status :: 3 - Alpha
Classifier: Intended Audience :: Science/Research
Classifier: License :: OSI Approved :: Apache Software License
Classifier: Programming Language :: Python :: 3
Requires-Python: >=3.7
License-File: LICENSE
License-File: NOTICE
Requires-Dist: torch
